README.md
setup.py
InformationRetrieval/__init__.py
InformationRetrieval/Document/AbstractCollection.c
InformationRetrieval/Document/AbstractCollection.pxd
InformationRetrieval/Document/AbstractCollection.pyx
InformationRetrieval/Document/CategoryHierarchy.c
InformationRetrieval/Document/CategoryHierarchy.pxd
InformationRetrieval/Document/CategoryHierarchy.pyx
InformationRetrieval/Document/DiskCollection.c
InformationRetrieval/Document/DiskCollection.pxd
InformationRetrieval/Document/DiskCollection.pyx
InformationRetrieval/Document/Document.c
InformationRetrieval/Document/Document.pxd
InformationRetrieval/Document/Document.pyx
InformationRetrieval/Document/DocumentText.c
InformationRetrieval/Document/DocumentText.pxd
InformationRetrieval/Document/DocumentText.pyx
InformationRetrieval/Document/DocumentType.py
InformationRetrieval/Document/DocumentWeighting.py
InformationRetrieval/Document/IndexType.py
InformationRetrieval/Document/LargeCollection.c
InformationRetrieval/Document/LargeCollection.pxd
InformationRetrieval/Document/LargeCollection.pyx
InformationRetrieval/Document/MediumCollection.c
InformationRetrieval/Document/MediumCollection.pxd
InformationRetrieval/Document/MediumCollection.pyx
InformationRetrieval/Document/MemoryCollection.c
InformationRetrieval/Document/MemoryCollection.pxd
InformationRetrieval/Document/MemoryCollection.pyx
InformationRetrieval/Document/Parameter.c
InformationRetrieval/Document/Parameter.pxd
InformationRetrieval/Document/Parameter.pyx
InformationRetrieval/Document/__init__.py
InformationRetrieval/Index/CategoryNode.c
InformationRetrieval/Index/CategoryNode.pxd
InformationRetrieval/Index/CategoryNode.pyx
InformationRetrieval/Index/CategoryTree.c
InformationRetrieval/Index/CategoryTree.pxd
InformationRetrieval/Index/CategoryTree.pyx
InformationRetrieval/Index/IncidenceMatrix.c
InformationRetrieval/Index/IncidenceMatrix.pxd
InformationRetrieval/Index/IncidenceMatrix.pyx
InformationRetrieval/Index/InvertedIndex.c
NlpToolkit_InformationRetrieval_Cy.egg-info/PKG-INFO
NlpToolkit_InformationRetrieval_Cy.egg-info/SOURCES.txt
NlpToolkit_InformationRetrieval_Cy.egg-info/dependency_links.txt
NlpToolkit_InformationRetrieval_Cy.egg-info/requires.txt
NlpToolkit_InformationRetrieval_Cy.egg-info/top_level.txt
nlptoolkit_informationretrieval_cy.egg-info/PKG-INFO
nlptoolkit_informationretrieval_cy.egg-info/SOURCES.txt
nlptoolkit_informationretrieval_cy.egg-info/dependency_links.txt
nlptoolkit_informationretrieval_cy.egg-info/requires.txt
nlptoolkit_informationretrieval_cy.egg-info/top_level.txt