Metadata-Version: 2.4
Name: nlptoolkit-informationretrieval-cy
Version: 1.0.7
Summary: Information Retrieval Library
Home-page: https://github.com/StarlangSoftware/InformationRetrieval-Cy
Author: olcaytaner
Author-email: olcay.yildiz@ozyegin.edu.tr
Requires-Dist: NlpToolkit-MorphologicalDisambiguation-Cy
Dynamic: author
Dynamic: author-email
Dynamic: description
Dynamic: description-content-type
Dynamic: home-page
Dynamic: requires-dist
Dynamic: summary
